virtual_ipm/LICENSE
virtual_ipm/VERSION
virtual_ipm/__init__.py
virtual_ipm/auxiliaries.py
virtual_ipm/components.py
virtual_ipm/log.py
virtual_ipm/run.py
virtual_ipm/settle.py
virtual_ipm/start_gui.py
virtual_ipm/timings.py
virtual_ipm/benchmarking/__init__.py
virtual_ipm/benchmarking/particle_tracking/RadialFieldsBx0.xml
virtual_ipm/benchmarking/particle_tracking/RungeKutta4.xml
virtual_ipm/benchmarking/particle_tracking/__init__.py
virtual_ipm/benchmarking/particle_tracking/basic_e_only_tracker.xml
virtual_ipm/benchmarking/particle_tracking/boris.xml
virtual_ipm/benchmarking/particle_tracking/config.xml
virtual_ipm/benchmarking/particle_tracking/plot.py
virtual_ipm/benchmarking/particle_tracking/run_tests.py
virtual_ipm/benchmarking/particle_tracking/show_all_test_cases.py
virtual_ipm/benchmarking/particle_tracking/test.py
virtual_ipm/benchmarking/particle_tracking/test_model.py
virtual_ipm/control/__init__.py
virtual_ipm/control/commands.py
virtual_ipm/control/threading.py
virtual_ipm/data/__init__.py
virtual_ipm/data/gas_types.py
virtual_ipm/data/particle_types.py
virtual_ipm/di/__init__.py
virtual_ipm/di/bindings.py
virtual_ipm/di/components.py
virtual_ipm/di/models.py
virtual_ipm/frontends/__init__.py
virtual_ipm/frontends/gui/__init__.py
virtual_ipm/frontends/gui/about.py
virtual_ipm/frontends/gui/mainwindow.py
virtual_ipm/frontends/gui/pyqt45.py
virtual_ipm/frontends/gui/utils.py
virtual_ipm/frontends/gui/views.py
virtual_ipm/frontends/gui/analysis/__init__.py
virtual_ipm/frontends/gui/analysis/views.py
virtual_ipm/frontends/gui/icons/about.png
virtual_ipm/frontends/gui/icons/add_plus.png
virtual_ipm/frontends/gui/icons/data-analysis.png
virtual_ipm/frontends/gui/icons/info.png
virtual_ipm/frontends/gui/icons/open_and_save_file.svg
virtual_ipm/frontends/gui/icons/open_file.png
virtual_ipm/frontends/gui/icons/open_xml.png
virtual_ipm/frontends/gui/icons/parameter_sweep.png
virtual_ipm/frontends/gui/icons/run.png
virtual_ipm-2.3.1.dist-info/licenses/LICENSE.md
virtual_ipm-2.3.1.dist-info/METADATA
virtual_ipm-2.3.1.dist-info/WHEEL
virtual_ipm-2.3.1.dist-info/entry_points.txt
virtual_ipm-2.3.1.dist-info/top_level.txt
virtual_ipm-2.3.1.dist-info/RECORD
