Metadata-Version: 2.4
Name: virtual-ipm
Version: 2.3.1
Summary: Virtual-IPM is a software for simulating transverse profile monitors under the influence of beam space-charge and external fields.
Home-page: https://gitlab.com/IPMsim/Virtual-IPM
Author: Dominik Vilsmeier
Author-email: dominik.vilsmeier1123@gmail.com
License: AGPL-3.0
Project-URL: Documentation, https://ipmsim.gitlab.io/Virtual-IPM/
Project-URL: Code, https://gitlab.com/IPMsim/Virtual-IPM
Project-URL: Issue tracker, https://gitlab.com/IPMsim/Virtual-IPM/-/issues
Project-URL: Changelog, https://ipmsim.gitlab.io/Virtual-IPM/changelog.html
Keywords: IPM,BGI,BIF,beam instrumentation,beam diagnostics,transverse profile monitor,simulation,framework,ionization profile monitor,beam gas ionization profile monitor,beam induced fluorescence monitor,space charge,particle accelerator
Classifier: Development Status :: 5 - Production/Stable
Classifier: License :: OSI Approved :: GNU Affero General Public License v3 or later (AGPLv3+)
Classifier: Programming Language :: Python :: 3.9
Classifier: Programming Language :: Python :: 3.10
Classifier: Programming Language :: Python :: 3.11
Classifier: Programming Language :: Python :: 3.12
Classifier: Programming Language :: Python :: 3.13
Classifier: Topic :: Scientific/Engineering :: Physics
Requires-Python: >=3.9
License-File: LICENSE.md
Requires-Dist: anna>=0.5.2
Requires-Dist: injector==0.12.1
Requires-Dist: ionics
Requires-Dist: numpy>=1.18
Requires-Dist: pandas
Requires-Dist: pyhocon
Requires-Dist: rich>=13.8
Requires-Dist: rx<3.0
Requires-Dist: scipy
Requires-Dist: six
Provides-Extra: gui
Requires-Dist: PyQt5; extra == "gui"
Requires-Dist: matplotlib>=3.2; extra == "gui"
Provides-Extra: obstacles
Requires-Dist: trimesh[easy]; extra == "obstacles"
Provides-Extra: tests
Requires-Dist: pytest; extra == "tests"
Requires-Dist: matplotlib; extra == "tests"
Dynamic: author
Dynamic: author-email
Dynamic: classifier
Dynamic: description
Dynamic: description-content-type
Dynamic: home-page
Dynamic: keywords
Dynamic: license
Dynamic: license-file
Dynamic: provides-extra
Dynamic: requires-dist
Dynamic: requires-python
Dynamic: summary
